purecpp_embed_dev/__init__.py
purecpp_embed_dev/purecpp_embed_dev.cpython-311-x86_64-linux-gnu.so
purecpp_embed_dev-0.0.400.dist-info/METADATA
purecpp_embed_dev-0.0.400.dist-info/WHEEL
purecpp_embed_dev-0.0.400.dist-info/top_level.txt
purecpp_embed_dev-0.0.400.dist-info/RECORD
