Metadata-Version: 2.4
Name: purecpp_embed_dev
Version: 0.0.400
Summary: C++ embeddings generator for RAG and other structures. This package is a part of the PureCPP ecosystem.
Home-page: https://github.com/pureai-ecosystem/purecpp
Author: PureAI
Author-email: contato@pureai.com.br
License: MIT
Classifier: Programming Language :: Python :: 3
Classifier: Operating System :: POSIX :: Linux
Requires-Dist: purecpp_libs_dev
Dynamic: author
Dynamic: author-email
Dynamic: classifier
Dynamic: home-page
Dynamic: license
Dynamic: requires-dist
Dynamic: summary
